datamem.v
module datamem(
    input wire clk,
    input wire reset,
    input wire writeEn,
    input wire [31:0] addr,
    input wire [2:0] func3,
    input wire [31:0] storeVal,
    output reg [31:0] loadVal,
    output reg data_ready
);

reg [31:0] memory [0:1023];
integer i;

initial begin
    for (i = 0; i < 1024; i = i + 1) begin
        memory[i] = 32'h0;
    end
    data_ready = 0;
end

always @(posedge clk or posedge reset) begin
    if (reset) begin
        for (i = 0; i < 1024; i = i + 1) begin
            memory[i] <= 32'h0;
        end
        loadVal <= 32'h0;
        data_ready <= 0;
    end
    else begin
        data_ready <= 0;
        if (writeEn) begin
            memory[addr[11:2]] <= storeVal;
            data_ready <= 1;
        end
        else begin
            loadVal <= memory[addr[11:2]];
            data_ready <= 1;
        end
    end
end

endmodule

//https://stackoverflow.com/questions/4176556/how-to-sign-extend-a-number-in-verilog

cache.v
module cache (
    input wire clk,
    input wire reset,
    input wire [31:0] addr,
    input wire [31:0] write_data,
    input wire write_en,
    input wire [2:0] func3,
    output reg [31:0] read_data,
    output reg hit,
    output reg busy
);

// Cache structure (2-way set associative)
reg [0:0] valid [3:0][1:0];      // 4 sets, 2 ways, 1 valid bit each
reg [25:0] tags [3:0][1:0];      // 26-bit tags
reg [31:0] data [3:0][1:0];      // 32-bit data
reg [2:0] age [3:0][1:0];        // LRU counter (3-bit)

// State machine
reg [1:0] state;
localparam IDLE = 2'b00;
localparam READ = 2'b01;
localparam WRITE = 2'b10;

// Cache line selection
reg replace_way;
wire [25:0] tag = addr[31:6];    // Tag bits
wire [1:0] set_index = addr[5:4]; // Set index bits
wire addr_valid = (addr[1:0] == 2'b00);  // Word alignment check

// Memory interface
wire [31:0] mem_data;
wire mem_data_ready;
reg mem_write_en;

// Initial state
integer i, j;
initial begin
    for(i = 0; i < 4; i = i + 1) begin
        for(j = 0; j < 2; j = j + 1) begin
            valid[i][j] = 0;
            tags[i][j] = 0;
            data[i][j] = 0;
            age[i][j] = 0;
        end
    end
    state = IDLE;
    busy = 0;
    hit = 0;
    mem_write_en = 0;
    read_data = 0;
end

// Memory interface
datamem main_memory(
    .clk(clk),
    .reset(reset),
    .writeEn(mem_write_en),
    .addr(addr),
    .func3(func3),
    .storeVal(write_data),
    .loadVal(mem_data),
    .data_ready(mem_data_ready)
);

// Main control logic
always @(posedge clk or posedge reset) begin
    if (reset) begin
        state <= IDLE;
        busy <= 0;
        hit <= 0;
        mem_write_en <= 0;
        read_data <= 0;
        for(i = 0; i < 4; i = i + 1) begin
            for(j = 0; j < 2; j = j + 1) begin
                valid[i][j] <= 0;
                tags[i][j] <= 0;
                data[i][j] <= 0;
                age[i][j] <= 0;
            end
        end
    end
    else begin
        case(state)
            IDLE: begin
                mem_write_en <= 0;
                busy <= 0;
                hit <= 0;

                if (addr_valid) begin
                    // Check both ways for hit
                    if (valid[set_index][0] && tags[set_index][0] == tag) begin
                        hit <= 1;
                        read_data <= data[set_index][0];
                        age[set_index][0] <= 0;
                        age[set_index][1] <= age[set_index][1] + 1;
                        
                        if (write_en) begin
                            data[set_index][0] <= write_data;
                            mem_write_en <= 1;
                            state <= WRITE;
                            busy <= 1;
                        end
                    end
                    else if (valid[set_index][1] && tags[set_index][1] == tag) begin
                        hit <= 1;
                        read_data <= data[set_index][1];
                        age[set_index][1] <= 0;
                        age[set_index][0] <= age[set_index][0] + 1;
                        
                        if (write_en) begin
                            data[set_index][1] <= write_data;
                            mem_write_en <= 1;
                            state <= WRITE;
                            busy <= 1;
                        end
                    end
                    else begin
                        // Cache miss
                        hit <= 0;
                        busy <= 1;
                        state <= READ;
                        // Select replacement way
                        replace_way <= (!valid[set_index][0]) ? 1'b0 :
                                     (!valid[set_index][1]) ? 1'b1 :
                                     (age[set_index][0] > age[set_index][1]) ? 1'b0 : 1'b1;
                    end
                end
            end

            READ: begin
                if (mem_data_ready) begin
                    valid[set_index][replace_way] <= 1'b1;
                    tags[set_index][replace_way] <= tag;
                    data[set_index][replace_way] <= mem_data;
                    read_data <= mem_data;
                    
                    age[set_index][replace_way] <= 0;
                    age[set_index][~replace_way] <= age[set_index][~replace_way] + 1;

                    state <= IDLE;
                    busy <= 0;
                    hit <= 1;
                end
                else begin
                    busy <= 1;
                end
            end

            WRITE: begin
                if (mem_data_ready) begin
                    state <= IDLE;
                    busy <= 0;
                    mem_write_en <= 0;
                end
                else begin
                    busy <= 1;
                end
            end

            default: begin
                state <= IDLE;
                busy <= 0;
                hit <= 0;
                mem_write_en <= 0;
            end
        endcase
    end
end

endmodule

cache_tb.v
`timescale 1ns/1ps

module cache_tb;
    // Basic signals
    reg clk;
    reg reset;
    reg [31:0] addr;
    reg [31:0] write_data;
    reg write_en;
    reg [2:0] func3;
    wire [31:0] read_data;
    wire hit;
    wire busy;

    // Test control variables
    integer timeout;
    integer error_count;
    integer i, j;
    integer addr_temp, data_temp;
    integer random_seed;
    reg [1:0] pre_state;
    reg pre_hit;
    reg [31:0] test_vectors[0:31];

    // DUT instantiation
    cache dut(
        .clk(clk),
        .reset(reset),
        .addr(addr),
        .write_data(write_data),
        .write_en(write_en),
        .func3(func3),
        .read_data(read_data),
        .hit(hit),
        .busy(busy)
    );

    // Fix tag extraction
    wire [25:0] tag = addr[31:6];  // Corrected tag bits
    wire [1:0] set_index = addr[5:4];  // Set index bits

    // Add state definitions to match cache.v
    localparam IDLE = 2'b00;
    localparam MEMOP = 2'b01;
    localparam UPDATE = 2'b10;

    // Simplified print_cache_state task
    task print_cache_state;
        integer i;
        begin
            $display("\nCache State at time %0t:", $time);
            for (i = 0; i < 4; i = i + 1) begin
                $display("Set %0d: Valid[0]=%b Tag[0]=%h Data[0]=%h Age[0]=%d", 
                        i, dut.valid[i][0], dut.tags[i][0], dut.data[i][0], dut.age[i][0]);
                $display("      Valid[1]=%b Tag[1]=%h Data[1]=%h Age[1]=%d", 
                        dut.valid[i][1], dut.tags[i][1], dut.data[i][1], dut.age[i][1]);
            end
            $display("");
        end
    endtask

    // Remove shadow memory and coherency checking

    // Initialize test vectors
    initial begin
        random_seed = 32'h1234_5678;  // Fixed seed for reproducibility
        for(i = 0; i < 32; i = i + 1) begin
            test_vectors[i] = $random(random_seed);
        end
    end

    // Define expected data register
    reg [31:0] expected_data;

    // Update expected_data on write operations
    always @(posedge clk) begin
        if (write_en) begin
            expected_data <= write_data;
        end
    end

    // Improved memory operation task
    task do_memory_op;
        input [31:0] address;
        input [31:0] data;
        input write;
        input [2:0] size;
        begin
            // Record pre-op state for debug
            pre_state = dut.state;
            pre_hit = hit;
            
            @(posedge clk);
            addr = address;
            write_data = data;
            write_en = write;
            func3 = size;
            
            // Wait for busy or hit
            repeat(2) @(posedge clk);
            
            // Wait for operation to complete
            timeout = 0;
            while((busy || (!hit && !write)) && timeout < 20) begin
                @(posedge clk);
                timeout = timeout + 1;
            end
            
            // Enhanced error checking
            if(timeout == 20) begin
                $display("ERROR: Operation timeout at time %0t", $time);
                $display("Pre-op state: %d, Pre-hit: %b", pre_state, pre_hit);
                $display("Current state: %d, Hit: %b", dut.state, hit);
                error_count = error_count + 1;
                $finish;
            end
            else begin
                $display("Operation complete after %0d cycles", timeout);
                $display("Hit: %b, Read Data: %h", hit, read_data);
                if(!write && hit) begin
                    case(size)
                        3'b000: begin // Byte
                            if((read_data & 32'h000000FF) !== (expected_data & 32'h000000FF)) begin
                                $display("ERROR: Byte read mismatch. Expected %h, got %h", 
                                    expected_data & 32'h000000FF, read_data & 32'h000000FF);
                                error_count = error_count + 1;
                            end
                        end
                        3'b001: begin // Half word
                            if((read_data & 32'h0000FFFF) !== (expected_data & 32'h0000FFFF)) begin
                                $display("ERROR: Half word read mismatch. Expected %h, got %h", 
                                    expected_data & 32'h0000FFFF, read_data & 32'h0000FFFF);
                                error_count = error_count + 1;
                            end
                        end
                        default: begin // Word
                            if(read_data !== expected_data) begin
                                $display("ERROR: Word read mismatch. Expected %h, got %h", 
                                    expected_data, read_data);
                                error_count = error_count + 1;
                            end
                        end
                    endcase
                end
                print_cache_state();
            end

            @(posedge clk);
        end
    endtask

    // Initialize expected_data
    initial begin
        expected_data = 32'h0;
    end

    // Clock generation
    initial begin
        clk = 0;
        forever #5 clk = ~clk;
    end

    // Test stimulus
    initial begin
        $dumpfile("cache_test.vcd");
        $dumpvars(0, cache_tb);

        // Initialize
        error_count = 0;
        reset = 1;
        addr = 0;
        write_data = 0;
        write_en = 0;
        func3 = 3'b010;

        // Reset sequence
        repeat(10) @(posedge clk);  // Hold reset longer
        reset = 0;
        repeat(5) @(posedge clk);   // Wait after reset

        // Initialize memory to known state
        // Optionally, add memory initialization tasks if required

        // Generate test vectors
        for(i = 0; i < 32; i = i + 1) begin
            test_vectors[i] = $random(random_seed);  // Random data
        end

        $display("\n=== PHASE 1: Sequential Set Testing ===");
        // Test each set systematically
        for(i = 0; i < 4; i = i + 1) begin
            // Calculate base address for this set (set_index = addr[5:4])
            addr_temp = (i << 4);  // Shift set index to correct position
            $display("\nTesting Set %0d", i);
            
            // Write unique data to first way
            do_memory_op(addr_temp, 32'h11111111 + i, 1, 3'b010);
            // Verify first way
            do_memory_op(addr_temp, 32'h11111111 + i, 0, 3'b010);
            
            // Write to second way with different tag
            do_memory_op(addr_temp + 32'h1000, 32'h22222222 + i, 1, 3'b010);
            // Verify second way
            do_memory_op(addr_temp + 32'h1000, 32'h22222222 + i, 0, 3'b010);
            
            // Verify first way again (shouldn't be evicted)
            do_memory_op(addr_temp, 32'h11111111 + i, 0, 3'b010);
        end

        $display("\n=== PHASE 2: LRU Testing ===");
        // Test LRU replacement for each set
        for(i = 0; i < 4; i = i + 1) begin
            addr_temp = (i << 4);
            $display("\nTesting LRU for Set %0d", i);
            
            // Fill both ways
            do_memory_op(addr_temp, 32'hAAAA0000 + i, 1, 3'b010);
            do_memory_op(addr_temp + 32'h1000, 32'hBBBB0000 + i, 1, 3'b010);
            
            // Access first way to make second way LRU
            do_memory_op(addr_temp, 32'hAAAA0000 + i, 0, 3'b010);
            
            // Write to third address, should replace second way
            do_memory_op(addr_temp + 32'h2000, 32'hCCCC0000 + i, 1, 3'b010);
            
            // Verify first way still present
            do_memory_op(addr_temp, 32'hAAAA0000 + i, 0, 3'b010);
            // Verify third address replaced second
            do_memory_op(addr_temp + 32'h2000, 32'hCCCC0000 + i, 0, 3'b010);
        end

        $display("\n=== PHASE 3: Tag Exhaustion Test ===");
        // Test with different tag values
        for(i = 0; i < 8; i = i + 1) begin
            addr_temp = i << 8;  // Use different tag bits
            data_temp = 32'hAA000000 + (i << 16);
            do_memory_op(addr_temp, data_temp, 1, 3'b010);
            do_memory_op(addr_temp, data_temp, 0, 3'b010);
        end

        $display("\n=== PHASE 4: Edge Cases ===");
        // Test maximum valid address
        do_memory_op(32'hFFC, 32'hEEEEEEEE, 1, 3'b010);
        do_memory_op(32'hFFC, 32'hEEEEEEEE, 0, 3'b010);
        
        // Test different access sizes
        do_memory_op(32'h100, 32'h12345678, 1, 3'b000); // Byte
        do_memory_op(32'h100, 32'h12345678, 0, 3'b000);
        do_memory_op(32'h104, 32'h90ABCDEF, 1, 3'b001); // Half word
        do_memory_op(32'h104, 32'h90ABCDEF, 0, 3'b001);

        $display("\n=== Test Summary ===");
        $display("Total Errors: %0d", error_count);
        $finish;
    end

    // Simplified assertions
    always @(posedge clk) begin
        if(!reset) begin
            if(hit === 1'bx || busy === 1'bx || dut.state === 2'bxx) begin
                $display("ERROR: Undefined signals at time %0t", $time);
                $display("State: %b, Hit: %b, Busy: %b", dut.state, hit, busy);
                error_count = error_count + 1;
            end
        end
    end

    // Add expected value tracking
    always @(posedge clk) begin
        if (hit && !write_en) begin
            if (read_data === 32'hxxxxxxxx) begin
                $display("ERROR: Undefined read data at time %0t", $time);
                $display("Address: %h, Expected: %h", addr, expected_data);
                error_count = error_count + 1;
            end
        end
    end
endmodule

cache_test.vcd
$date
	Fri Dec 20 04:56:59 2024
$end
$version
	Icarus Verilog
$end
$timescale
	1ps
$end
$scope module cache_tb $end
$var wire 26 ! tag [25:0] $end
$var wire 2 " set_index [1:0] $end
$var wire 32 # read_data [31:0] $end
$var wire 1 $ hit $end
$var wire 1 % busy $end
$var parameter 2 & IDLE $end
$var parameter 2 ' MEMOP $end
$var parameter 2 ( UPDATE $end
$var reg 32 ) addr [31:0] $end
$var reg 1 * clk $end
$var reg 32 + expected_data [31:0] $end
$var reg 3 , func3 [2:0] $end
$var reg 1 - pre_hit $end
$var reg 2 . pre_state [1:0] $end
$var reg 1 / reset $end
$var reg 32 0 write_data [31:0] $end
$var reg 1 1 write_en $end
$var integer 32 2 addr_temp [31:0] $end
$var integer 32 3 data_temp [31:0] $end
$var integer 32 4 error_count [31:0] $end
$var integer 32 5 i [31:0] $end
$var integer 32 6 random_seed [31:0] $end
$var integer 32 7 timeout [31:0] $end
$scope module dut $end
$var wire 32 8 addr [31:0] $end
$var wire 1 * clk $end
$var wire 3 9 func3 [2:0] $end
$var wire 1 / reset $end
$var wire 32 : write_data [31:0] $end
$var wire 1 1 write_en $end
$var wire 26 ; tag [25:0] $end
$var wire 2 < set_index [1:0] $end
$var wire 1 = mem_data_ready $end
$var wire 32 > mem_data [31:0] $end
$var wire 1 ? addr_valid $end
$var parameter 2 @ IDLE $end
$var parameter 2 A READ $end
$var parameter 2 B WRITE $end
$var reg 1 % busy $end
$var reg 1 $ hit $end
$var reg 1 C mem_write_en $end
$var reg 32 D read_data [31:0] $end
$var reg 1 E replace_way $end
$var reg 2 F state [1:0] $end
$var integer 32 G i [31:0] $end
$var integer 32 H j [31:0] $end
$scope module main_memory $end
$var wire 32 I addr [31:0] $end
$var wire 1 * clk $end
$var wire 3 J func3 [2:0] $end
$var wire 1 / reset $end
$var wire 32 K storeVal [31:0] $end
$var wire 1 C writeEn $end
$var reg 1 = data_ready $end
$var reg 32 L loadVal [31:0] $end
$var integer 32 M i [31:0] $end
$upscope $end
$upscope $end
$scope task do_memory_op $end
$var reg 32 N address [31:0] $end
$var reg 32 O data [31:0] $end
$var reg 3 P size [2:0] $end
$var reg 1 Q write $end
$upscope $end
$scope task print_cache_state $end
$var integer 32 R i [31:0] $end
$upscope $end
$upscope $end
$enddefinitions $end
$comment Show the parameter values. $end
$dumpall
b10 B
b1 A
b0 @
b10 (
b1 '
b0 &
$end
#0
$dumpvars
bx R
xQ
bx P
bx O
bx N
b10000000000 M
b0 L
b0 K
b10 J
b0 I
b10 H
b100 G
b0 F
xE
b0 D
0C
1?
b0 >
0=
b0 <
b0 ;
b0 :
b10 9
b0 8
bx 7
b11001000101111010101110111011000 6
b100000 5
b0 4
bx 3
bx 2
01
b0 0
1/
bx .
x-
b10 ,
b0 +
0*
b0 )
0%
0$
b0 #
b0 "
b0 !
$end
#5000
b10 H
b100 G
b10000000000 M
1*
#10000
0*
#15000
b10000000000 M
b10 H
b100 G
1*
#20000
0*
#25000
b10 H
b100 G
b10000000000 M
1*
#30000
0*
#35000
b10000000000 M
b10 H
b100 G
1*
#40000
0*
#45000
b10 H
b100 G
b10000000000 M
1*
#50000
0*
#55000
b10000000000 M
b10 H
b100 G
1*
#60000
0*
#65000
b10 H
b100 G
b10000000000 M
1*
#70000
0*
#75000
b10000000000 M
b10 H
b100 G
1*
#80000
0*
#85000
b10 H
b100 G
b10000000000 M
1*
#90000
0*
#95000
1=
0E
b1 F
1%
0/
1*
#100000
0*
#105000
1$
0%
b0 F
1=
1*
#110000
0*
#115000
1=
1$
1*
#120000
0*
#125000
1$
1=
1*
#130000
0*
#135000
1=
1$
1*
#140000
0*
#145000
1$
1=
1-
b0 .
b10 P
1Q
b10001000100010001000100010001 O
b0 N
b0 2
b1011111110101000001010100111000 6
b0 5
1*
#150000
0*
#155000
1=
1%
b10 F
1C
1$
b10001000100010001000100010001 +
11
b10001000100010001000100010001 0
b10001000100010001000100010001 :
b10001000100010001000100010001 K
1*
#160000
0*
#165000
0C
0%
b0 F
1=
1*
#170000
0*
#175000
b10001000100010001000100010001 >
b10001000100010001000100010001 L
1=
1%
b10 F
1C
b10001000100010001000100010001 #
b10001000100010001000100010001 D
1$
b100 R
b0 7
1*
#180000
0*
#185000
0C
0%
b0 F
1=
b10 .
0Q
1*
#190000
0*
#195000
1=
1$
01
1*
#200000
0*
#205000
1$
1=
1*
#210000
0*
#215000
1=
1$
b100 R
1*
#220000
0*
#225000
1$
1=
b0 .
1Q
b100010001000100010001000100010 O
b1000000000000 N
1*
#230000
0*
#235000
1=
1%
b10 F
1C
1$
b100010001000100010001000100010 +
b1000000 !
b1000000 ;
11
b100010001000100010001000100010 0
b100010001000100010001000100010 :
b100010001000100010001000100010 K
b1000000000000 )
b1000000000000 8
b1000000000000 I
1*
#240000
0*
#245000
0C
0%
b0 F
1=
1*
#250000
0*
#255000
b100010001000100010001000100010 >
b100010001000100010001000100010 L
1=
1E
b1 F
1%
0$
b100 R
1*
#260000
0*
#265000
1$
0%
b0 F
b100010001000100010001000100010 #
b100010001000100010001000100010 D
1=
0-
b1 .
0Q
1*
#270000
0*
#275000
1=
1$
01
1*
#280000
0*
#285000
1$
1=
1*
#290000
0*
#295000
1=
1$
b100 R
1*
#300000
0*
#305000
1$
1=
1-
b0 .
b10001000100010001000100010001 O
b0 N
1*
#310000
0*
#315000
1=
1$
b0 !
b0 ;
b10001000100010001000100010001 0
b10001000100010001000100010001 :
b10001000100010001000100010001 K
b0 )
b0 8
b0 I
1*
#320000
0*
#325000
1$
1=
1*
#330000
0*
#335000
1=
1$
b100 R
1*
#340000
0*
#345000
1$
1=
1Q
b10001000100010001000100010010 O
b10000 N
b10000 2
b1 5
1*
#350000
0*
#355000
b0 >
b0 L
1=
1%
b10 F
1C
1$
b10001000100010001000100010010 +
b1 "
b1 <
11
b10001000100010001000100010010 0
b10001000100010001000100010010 :
b10001000100010001000100010010 K
b10000 )
b10000 8
b10000 I
1*
#360000
0*
#365000
0C
0%
b0 F
1=
1*
#370000
0*
#375000
b10001000100010001000100010010 >
b10001000100010001000100010010 L
1=
0E
b1 F
1%
0$
b100 R
1*
#380000
0*
#385000
1$
0%
b0 F
b10001000100010001000100010010 #
b10001000100010001000100010010 D
1=
0-
b1 .
0Q
1*
#390000
0*
#395000
1=
1$
01
1*
#400000
0*
#405000
1$
1=
1*
#410000
0*
#415000
1=
1$
b100 R
1*
#420000
0*
#425000
1$
1=
1-
b0 .
1Q
b100010001000100010001000100011 O
b1000000010000 N
1*
#430000
0*
#435000
1=
1%
b10 F
1C
1$
b100010001000100010001000100011 +
b1000000 !
b1000000 ;
11
b100010001000100010001000100011 0
b100010001000100010001000100011 :
b100010001000100010001000100011 K
b1000000010000 )
b1000000010000 8
b1000000010000 I
1*
#440000
0*
#445000
0C
0%
b0 F
1=
1*
#450000
0*
#455000
b100010001000100010001000100011 >
b100010001000100010001000100011 L
1=
1E
b1 F
1%
0$
b100 R
1*
#460000
0*
#465000
1$
0%
b0 F
b100010001000100010001000100011 #
b100010001000100010001000100011 D
1=
0-
b1 .
0Q
1*
#470000
0*
#475000
1=
1$
01
1*
#480000
0*
#485000
1$
1=
1*
#490000
0*
#495000
1=
1$
b100 R
1*
#500000
0*
#505000
1$
1=
1-
b0 .
b10001000100010001000100010010 O
b10000 N
1*
#510000
0*
#515000
1=
1$
b0 !
b0 ;
b10001000100010001000100010010 0
b10001000100010001000100010010 :
b10001000100010001000100010010 K
b10000 )
b10000 8
b10000 I
1*
#520000
0*
#525000
1$
1=
1*
#530000
0*
#535000
1=
1$
b100 R
1*
#540000
0*
#545000
1$
1=
1Q
b10001000100010001000100010011 O
b100000 N
b100000 2
b10 5
1*
#550000
0*
#555000
b0 >
b0 L
1=
1%
b10 F
1C
1$
b10001000100010001000100010011 +
b10 "
b10 <
11
b10001000100010001000100010011 0
b10001000100010001000100010011 :
b10001000100010001000100010011 K
b100000 )
b100000 8
b100000 I
1*
#560000
0*
#565000
0C
0%
b0 F
1=
1*
#570000
0*
#575000
b10001000100010001000100010011 >
b10001000100010001000100010011 L
1=
0E
b1 F
1%
0$
b100 R
1*
#580000
0*
#585000
1$
0%
b0 F
b10001000100010001000100010011 #
b10001000100010001000100010011 D
1=
0-
b1 .
0Q
1*
#590000
0*
#595000
1=
1$
01
1*
#600000
0*
#605000
1$
1=
1*
#610000
0*
#615000
1=
1$
b100 R
1*
#620000
0*
#625000
1$
1=
1-
b0 .
1Q
b100010001000100010001000100100 O
b1000000100000 N
1*
#630000
0*
#635000
1=
1%
b10 F
1C
1$
b100010001000100010001000100100 +
b1000000 !
b1000000 ;
11
b100010001000100010001000100100 0
b100010001000100010001000100100 :
b100010001000100010001000100100 K
b1000000100000 )
b1000000100000 8
b1000000100000 I
1*
#640000
0*
#645000
0C
0%
b0 F
1=
1*
#650000
0*
#655000
b100010001000100010001000100100 >
b100010001000100010001000100100 L
1=
1E
b1 F
1%
0$
b100 R
1*
#660000
0*
#665000
1$
0%
b0 F
b100010001000100010001000100100 #
b100010001000100010001000100100 D
1=
0-
b1 .
0Q
1*
#670000
0*
#675000
1=
1$
01
1*
#680000
0*
#685000
1$
1=
1*
#690000
0*
#695000
1=
1$
b100 R
1*
#700000
0*
#705000
1$
1=
1-
b0 .
b10001000100010001000100010011 O
b100000 N
1*
#710000
0*
#715000
1=
1$
b0 !
b0 ;
b10001000100010001000100010011 0
b10001000100010001000100010011 :
b10001000100010001000100010011 K
b100000 )
b100000 8
b100000 I
1*
#720000
0*
#725000
1$
1=
1*
#730000
0*
#735000
1=
1$
b100 R
1*
#740000
0*
#745000
1$
1=
1Q
b10001000100010001000100010100 O
b110000 N
b110000 2
b11 5
1*
#750000
0*
#755000
b0 >
b0 L
1=
1%
b10 F
1C
1$
b10001000100010001000100010100 +
b11 "
b11 <
11
b10001000100010001000100010100 0
b10001000100010001000100010100 :
b10001000100010001000100010100 K
b110000 )
b110000 8
b110000 I
1*
#760000
0*
#765000
0C
0%
b0 F
1=
1*
#770000
0*
#775000
b10001000100010001000100010100 >
b10001000100010001000100010100 L
1=
0E
b1 F
1%
0$
b100 R
1*
#780000
0*
#785000
1$
0%
b0 F
b10001000100010001000100010100 #
b10001000100010001000100010100 D
1=
0-
b1 .
0Q
1*
#790000
0*
#795000
1=
1$
01
1*
#800000
0*
#805000
1$
1=
1*
#810000
0*
#815000
1=
1$
b100 R
1*
#820000
0*
#825000
1$
1=
1-
b0 .
1Q
b100010001000100010001000100101 O
b1000000110000 N
1*
#830000
0*
#835000
1=
1%
b10 F
1C
1$
b100010001000100010001000100101 +
b1000000 !
b1000000 ;
11
b100010001000100010001000100101 0
b100010001000100010001000100101 :
b100010001000100010001000100101 K
b1000000110000 )
b1000000110000 8
b1000000110000 I
1*
#840000
0*
#845000
0C
0%
b0 F
1=
1*
#850000
0*
#855000
b100010001000100010001000100101 >
b100010001000100010001000100101 L
1=
1E
b1 F
1%
0$
b100 R
1*
#860000
0*
#865000
1$
0%
b0 F
b100010001000100010001000100101 #
b100010001000100010001000100101 D
1=
0-
b1 .
0Q
1*
#870000
0*
#875000
1=
1$
01
1*
#880000
0*
#885000
1$
1=
1*
#890000
0*
#895000
1=
1$
b100 R
1*
#900000
0*
#905000
1$
1=
1-
b0 .
b10001000100010001000100010100 O
b110000 N
1*
#910000
0*
#915000
1=
1$
b0 !
b0 ;
b10001000100010001000100010100 0
b10001000100010001000100010100 :
b10001000100010001000100010100 K
b110000 )
b110000 8
b110000 I
1*
#920000
0*
#925000
1$
1=
1*
#930000
0*
#935000
1=
1$
b100 R
1*
#940000
0*
#945000
1$
1=
1Q
b10101010101010100000000000000000 O
b0 N
b0 2
b0 5
1*
#950000
0*
#955000
b100010001000100010001000100010 >
b100010001000100010001000100010 L
1=
1%
b10 F
1C
1$
b10101010101010100000000000000000 +
b0 "
b0 <
11
b10101010101010100000000000000000 0
b10101010101010100000000000000000 :
b10101010101010100000000000000000 K
b0 )
b0 8
b0 I
1*
#960000
0*
#965000
0C
0%
b0 F
1=
1*
#970000
0*
#975000
b10101010101010100000000000000000 >
b10101010101010100000000000000000 L
1=
1%
b10 F
1C
b10001000100010001000100010010 #
b10001000100010001000100010010 D
1$
b100 R
1*
#980000
0*
#985000
0C
0%
b0 F
1=
b10 .
b10111011101110110000000000000000 O
b1000000000000 N
1*
#990000
0*
#995000
1=
1%
b10 F
1C
b10101010101010100000000000000000 #
b10101010101010100000000000000000 D
1$
b10111011101110110000000000000000 +
b1000000 !
b1000000 ;
b10111011101110110000000000000000 0
b10111011101110110000000000000000 :
b10111011101110110000000000000000 K
b1000000000000 )
b1000000000000 8
b1000000000000 I
1*
#1000000
0*
#1005000
0C
0%
b0 F
1=
1*
#1010000
0*
#1015000
b10111011101110110000000000000000 >
b10111011101110110000000000000000 L
1=
1%
b10 F
1C
b100010001000100010001000100010 #
b100010001000100010001000100010 D
1$
b100 R
1*
#1020000
0*
#1025000
0C
0%
b0 F
1=
0Q
b10101010101010100000000000000000 O
b0 N
1*
#1030000
0*
#1035000
1=
b10111011101110110000000000000000 #
b10111011101110110000000000000000 D
1$
b0 !
b0 ;
01
b10101010101010100000000000000000 0
b10101010101010100000000000000000 :
b10101010101010100000000000000000 K
b0 )
b0 8
b0 I
1*
#1040000
0*
#1045000
1$
1=
1*
#1050000
0*
#1055000
1=
1$
b100 R
1*
#1060000
0*
#1065000
1$
1=
b0 .
1Q
b11001100110011000000000000000000 O
b10000000000000 N
1*
#1070000
0*
#1075000
1=
1%
b10 F
1C
1$
b11001100110011000000000000000000 +
b10000000 !
b10000000 ;
11
b11001100110011000000000000000000 0
b11001100110011000000000000000000 :
b11001100110011000000000000000000 K
b10000000000000 )
b10000000000000 8
b10000000000000 I
1*
#1080000
0*
#1085000
0C
0%
b0 F
1=
1*
#1090000
0*
#1095000
b11001100110011000000000000000000 >
b11001100110011000000000000000000 L
1=
b1 F
1%
0$
b100 R
1*
#1100000
0*
#1105000
1$
0%
b0 F
b11001100110011000000000000000000 #
b11001100110011000000000000000000 D
1=
0-
b1 .
0Q
b10101010101010100000000000000000 O
b0 N
1*
#1110000
0*
#1115000
1=
1$
b0 !
b0 ;
01
b10101010101010100000000000000000 0
b10101010101010100000000000000000 :
b10101010101010100000000000000000 K
b0 )
b0 8
b0 I
1*
#1120000
0*
#1125000
1$
1=
1*
#1130000
0*
#1135000
1=
1$
b100 R
1*
#1140000
0*
#1145000
1$
1=
1-
b0 .
b11001100110011000000000000000000 O
b10000000000000 N
1*
#1150000
0*
#1155000
1=
1$
b10000000 !
b10000000 ;
b11001100110011000000000000000000 0
b11001100110011000000000000000000 :
b11001100110011000000000000000000 K
b10000000000000 )
b10000000000000 8
b10000000000000 I
1*
#1160000
0*
#1165000
1$
1=
1*
#1170000
0*
#1175000
1=
1$
b100 R
1*
#1180000
0*
#1185000
1$
1=
1Q
b10101010101010100000000000000001 O
b10000 N
b10000 2
b1 5
1*
#1190000
0*
#1195000
b100010001000100010001000100011 >
b100010001000100010001000100011 L
1=
1%
b10 F
1C
1$
b10101010101010100000000000000001 +
b0 !
b1 "
b0 ;
b1 <
11
b10101010101010100000000000000001 0
b10101010101010100000000000000001 :
b10101010101010100000000000000001 K
b10000 )
b10000 8
b10000 I
1*
#1200000
0*
#1205000
0C
0%
b0 F
1=
1*
#1210000
0*
#1215000
b10101010101010100000000000000001 >
b10101010101010100000000000000001 L
1=
1%
b10 F
1C
b10001000100010001000100010011 #
b10001000100010001000100010011 D
1$
b100 R
1*
#1220000
0*
#1225000
0C
0%
b0 F
1=
b10 .
b10111011101110110000000000000001 O
b1000000010000 N
1*
#1230000
0*
#1235000
1=
1%
b10 F
1C
b10101010101010100000000000000001 #
b10101010101010100000000000000001 D
1$
b10111011101110110000000000000001 +
b1000000 !
b1000000 ;
b10111011101110110000000000000001 0
b10111011101110110000000000000001 :
b10111011101110110000000000000001 K
b1000000010000 )
b1000000010000 8
b1000000010000 I
1*
#1240000
0*
#1245000
0C
0%
b0 F
1=
1*
#1250000
0*
#1255000
b10111011101110110000000000000001 >
b10111011101110110000000000000001 L
1=
1%
b10 F
1C
b100010001000100010001000100011 #
b100010001000100010001000100011 D
1$
b100 R
1*
#1260000
0*
#1265000
0C
0%
b0 F
1=
0Q
b10101010101010100000000000000001 O
b10000 N
1*
#1270000
0*
#1275000
1=
b10111011101110110000000000000001 #
b10111011101110110000000000000001 D
1$
b0 !
b0 ;
01
b10101010101010100000000000000001 0
b10101010101010100000000000000001 :
b10101010101010100000000000000001 K
b10000 )
b10000 8
b10000 I
1*
#1280000
0*
#1285000
1$
1=
1*
#1290000
0*
#1295000
1=
1$
b100 R
1*
#1300000
0*
#1305000
1$
1=
b0 .
1Q
b11001100110011000000000000000001 O
b10000000010000 N
1*
#1310000
0*
#1315000
1=
1%
b10 F
1C
1$
b11001100110011000000000000000001 +
b10000000 !
b10000000 ;
11
b11001100110011000000000000000001 0
b11001100110011000000000000000001 :
b11001100110011000000000000000001 K
b10000000010000 )
b10000000010000 8
b10000000010000 I
1*
#1320000
0*
#1325000
0C
0%
b0 F
1=
1*
#1330000
0*
#1335000
b11001100110011000000000000000001 >
b11001100110011000000000000000001 L
1=
b1 F
1%
0$
b100 R
1*
#1340000
0*
#1345000
1$
0%
b0 F
b11001100110011000000000000000001 #
b11001100110011000000000000000001 D
1=
0-
b1 .
0Q
b10101010101010100000000000000001 O
b10000 N
1*
#1350000
0*
#1355000
1=
1$
b0 !
b0 ;
01
b10101010101010100000000000000001 0
b10101010101010100000000000000001 :
b10101010101010100000000000000001 K
b10000 )
b10000 8
b10000 I
1*
#1360000
0*
#1365000
1$
1=
1*
#1370000
0*
#1375000
1=
1$
b100 R
1*
#1380000
0*
#1385000
1$
1=
1-
b0 .
b11001100110011000000000000000001 O
b10000000010000 N
1*
#1390000
0*
